setup.py
cursoaulahu/__init__.py
cursoaulahu/dunder_main.py
cursoaulahu/github.py
cursoaulahu/github_import.py
cursoaulahu/telefonista.py
cursoaulahu/w3c.py
cursoaulahu.egg-info/PKG-INFO
cursoaulahu.egg-info/SOURCES.txt
cursoaulahu.egg-info/dependency_links.txt
cursoaulahu.egg-info/not-zip-safe
cursoaulahu.egg-info/requires.txt
cursoaulahu.egg-info/top_level.txt
test/testeloadr.py