Metadata-Version: 1.1
Name: cursoaulahu
Version: 0.4
Summary: Tekton app to handle user login and permissions based on groups and holes
Home-page: https://github.com/viollarr/cursoaulahu
Author: Victor Narcizo
Author-email: viollarr@gmail.com
License: BSD
Platform: UNKNOWN
Classifier: Development Status :: 4 - Beta
Classifier: Environment :: Web Environment
Classifier: Intended Audience :: Developers
Classifier: License :: OSI Approved :: BSD License
Classifier: Operating System :: OS Independent
Classifier: Programming Language :: Python
Classifier: Framework :: Paste
